time_series_insight/__init__.py
time_series_insight/api.py
time_series_insight/analysis/__init__.py
time_series_insight/analysis/model_identifier.py
time_series_insight/cli/__init__.py
time_series_insight/cli/main.py
time_series_insight/core/__init__.py
time_series_insight/core/data_processor.py
time_series_insight/estimation/__init__.py
time_series_insight/estimation/parameter_estimator.py
time_series_insight/evaluation/__init__.py
time_series_insight/evaluation/model_evaluator.py
time_series_insight/visualization/__init__.py
time_series_insight/visualization/plotter.py
time_series_insight_assistant-0.1.1.dist-info/METADATA
time_series_insight_assistant-0.1.1.dist-info/WHEEL
time_series_insight_assistant-0.1.1.dist-info/entry_points.txt
time_series_insight_assistant-0.1.1.dist-info/licenses/LICENSE
time_series_insight_assistant-0.1.1.dist-info/RECORD
