Metadata-Version: 2.4
Name: time-series-insight-assistant
Version: 0.1.1
Summary: 一个智能的时间序列分析助手，提供自动模型识别、参数估计和可视化诊断功能
Project-URL: Homepage, https://github.com/zym9863/time-series-insight-assistant
Project-URL: Repository, https://github.com/zym9863/time-series-insight-assistant
Project-URL: Bug Tracker, https://github.com/zym9863/time-series-insight-assistant/issues
Author-email: zym <ym214413520@gmail.com>
License: MIT
License-File: LICENSE
Keywords: analysis,arima,forecasting,statistics,time-series
Classifier: Development Status :: 4 - Beta
Classifier: Intended Audience :: Developers
Classifier: Intended Audience :: Science/Research
Classifier: License :: OSI Approved :: MIT License
Classifier: Operating System :: OS Independent
Classifier: Programming Language :: Python :: 3
Classifier: Programming Language :: Python :: 3.9
Classifier: Programming Language :: Python :: 3.10
Classifier: Programming Language :: Python :: 3.11
Classifier: Programming Language :: Python :: 3.12
Classifier: Topic :: Scientific/Engineering :: Mathematics
Classifier: Topic :: Software Development :: Libraries :: Python Modules
Requires-Python: >=3.9
Requires-Dist: click>=8.0.0
Requires-Dist: fastapi>=0.116.0
Requires-Dist: matplotlib>=3.4.0
Requires-Dist: numpy>=1.21.0
Requires-Dist: pandas>=1.3.0
Requires-Dist: python-multipart>=0.0.20
Requires-Dist: rich>=10.0.0
Requires-Dist: scipy>=1.7.0
Requires-Dist: seaborn>=0.11.0
Requires-Dist: statsmodels>=0.13.0
Requires-Dist: typer>=0.6.0
Requires-Dist: uvicorn[standard]>=0.35.0
Provides-Extra: dev
Requires-Dist: black>=21.0.0; extra == 'dev'
Requires-Dist: flake8>=3.9.0; extra == 'dev'
Requires-Dist: isort>=5.9.0; extra == 'dev'
Requires-Dist: mypy>=0.910; extra == 'dev'
Requires-Dist: pre-commit>=2.15.0; extra == 'dev'
Requires-Dist: pytest-cov>=2.12.0; extra == 'dev'
Requires-Dist: pytest>=6.0.0; extra == 'dev'
Provides-Extra: docs
Requires-Dist: myst-parser>=0.15.0; extra == 'docs'
Requires-Dist: sphinx-rtd-theme>=0.5.0; extra == 'docs'
Requires-Dist: sphinx>=4.0.0; extra == 'docs'
